Workbook

Sheet Produtos
A1: Casa do Boi FOS — Produtos, pesos e dimensões para envio
A2: Medidas do produto EMBALADO, pronto para postar. As células amarelas (peso e dimensões) estão preenchidas com ESTIMATIVAS — pese na balança e meça a caixa fechada, depois substitua o valor. As colunas cinzas se recalculam sozinhas.
A4: Código | B4: Produto | C4: Marca | D4: Departamento | E4: Unidade de venda | F4: Preço (R$) | G4: Peso bruto (kg) | H4: Comprimento (cm) | I4: Largura (cm) | J4: Altura (cm) | K4: Soma C+L+A (cm) | L4: Peso cubado (kg) | M4: Peso taxável (kg) | N4: Cabe nos Correios? | O4: Modalidade de envio | P4: Observação / restrição
A5: corrente-motosserra-16-polegadas | B5: Corrente para Motosserra 16 polegadas — 55 elos | C5: STIHL | D5: Máquinas e Ferramentas | E5: unidade | F5: 189.9 | G5: 0.75 | H5: 20 | I5: 15 | J5: 5 | K5: =H5+I5+J5 -> 40 | L5: =ROUND(H5*I5*J5/6000,2) -> 0.25 | M5: =ROUND(MAX(G5,L5),2) -> 0.75 | N5: =IF(OR(G5>30,MAX(H5,I5,J5)>100,K5>200),"NAO","SIM") -> SIM | O5: Correios
A6: frasco-misturador-stihl-1l | B6: Frasco Misturador STIHL 1 Litro | C6: STIHL | D6: Máquinas e Ferramentas | E6: unidade | F6: 59.9 | G6: 0.25 | H6: 28 | I6: 12 | J6: 10 | K6: =H6+I6+J6 -> 50 | L6: =ROUND(H6*I6*J6/6000,2) -> 0.56 | M6: =ROUND(MAX(G6,L6),2) -> 0.56 | N6: =IF(OR(G6>30,MAX(H6,I6,J6)>100,K6>200),"NAO","SIM") -> SIM | O6: Correios
A7: lavadora-alta-pressao-stihl-re-90 | B7: Lavadora de Alta Pressão STIHL RE 90 | C7: STIHL | D7: Máquinas e Ferramentas | E7: unidade | F7: 1199 | G7: 11.5 | H7: 40 | I7: 35 | J7: 85 | K7: =H7+I7+J7 -> 160 | L7: =ROUND(H7*I7*J7/6000,2) -> 19.83 | M7: =ROUND(MAX(G7,L7),2) -> 19.83 | N7: =IF(OR(G7>30,MAX(H7,I7,J7)>100,K7>200),"NAO","SIM") -> SIM | O7: Correios | P7: Lado de 85 cm: paga taxa de grande formato (acima de 70 cm).
A8: motosserra-stihl-ms-172 | B8: Motosserra STIHL MS 172 Light 16 polegadas | C8: STIHL | D8: Máquinas e Ferramentas | E8: unidade | F8: 2199 | G8: 6.5 | H8: 46 | I8: 30 | J8: 27 | K8: =H8+I8+J8 -> 103 | L8: =ROUND(H8*I8*J8/6000,2) -> 6.21 | M8: =ROUND(MAX(G8,L8),2) -> 6.5 | N8: =IF(OR(G8>30,MAX(H8,I8,J8)>100,K8>200),"NAO","SIM") -> SIM | O8: Correios
A9: pulverizador-costal-20l | B9: Pulverizador Costal Manual 20 Litros | C9: Guarany | D9: Máquinas e Ferramentas | E9: unidade | F9: 329.9 | G9: 5 | H9: 60 | I9: 45 | J9: 25 | K9: =H9+I9+J9 -> 130 | L9: =ROUND(H9*I9*J9/6000,2) -> 11.25 | M9: =ROUND(MAX(G9,L9),2) -> 11.25 | N9: =IF(OR(G9>30,MAX(H9,I9,J9)>100,K9>200),"NAO","SIM") -> SIM | O9: Correios | P9: Peso cubado (11,3 kg) manda no frete, não o peso real.
A10: rocadeira-stihl-fs-120 | B10: Roçadeira Lateral STIHL FS 120 | C10: STIHL | D10: Máquinas e Ferramentas | E10: unidade | F10: 3890 | G10: 9.5 | H10: 180 | I10: 30 | J10: 25 | K10: =H10+I10+J10 -> 235 | L10: =ROUND(H10*I10*J10/6000,2) -> 22.5 | M10: =ROUND(MAX(G10,L10),2) -> 22.5 | N10: =IF(OR(G10>30,MAX(H10,I10,J10)>100,K10>200),"NAO","SIM") -> NAO | O10: Transportadora | P10: Caixa de 180 cm: excede o lado máximo de 100 cm dos Correios.
A11: soprador-bateria-stihl-bga-60 | B11: Soprador a Bateria STIHL BGA 60 | C11: STIHL | D11: Máquinas e Ferramentas | E11: unidade | F11: 1690 | G11: 3.5 | H11: 55 | I11: 28 | J11: 30 | K11: =H11+I11+J11 -> 113 | L11: =ROUND(H11*I11*J11/6000,2) -> 7.7 | M11: =ROUND(MAX(G11,L11),2) -> 7.7 | N11: =IF(OR(G11>30,MAX(H11,I11,J11)>100,K11>200),"NAO","SIM") -> SIM | O11: Correios
A12: oleo-2-tempos-stihl-8017h-500ml | B12: Óleo 2 Tempos STIHL Castrol 8017H 500 ml | C12: STIHL | D12: Máquinas e Ferramentas | E12: frasco | F12: 79.9 | G12: 0.6 | H12: 20 | I12: 10 | J12: 8 | K12: =H12+I12+J12 -> 38 | L12: =ROUND(H12*I12*J12/6000,2) -> 0.27 | M12: =ROUND(MAX(G12,L12),2) -> 0.6 | N12: =IF(OR(G12>30,MAX(H12,I12,J12)>100,K12>200),"NAO","SIM") -> SIM | O12: Correios | P12: Líquido: exigir embalagem com absorvente e lacre.
A13: cocho-plastico-500l | B13: Cocho Plástico para Sal 500 Litros | C13: Fortlev | D13: Suplemento e Ração | E13: unidade | F13: 1290 | G13: 45 | H13: 200 | I13: 120 | J13: 90 | K13: =H13+I13+J13 -> 410 | L13: =ROUND(H13*I13*J13/6000,2) -> 360 | M13: =ROUND(MAX(G13,L13),2) -> 360 | N13: =IF(OR(G13>30,MAX(H13,I13,J13)>100,K13>200),"NAO","SIM") -> NAO | O13: Transportadora | P13: Volume grande: só transportadora ou entrega própria.
A14: nucleo-proteico-seca-25kg | B14: Núcleo Proteico Energético Seca — Saco 25 kg | C14: Boi FOS | D14: Suplemento e Ração | E14: saco 25 kg | F14: 174.9 | G14: 25.5 | H14: 60 | I14: 40 | J14: 15 | K14: =H14+I14+J14 -> 115 | L14: =ROUND(H14*I14*J14/6000,2) -> 6 | M14: =ROUND(MAX(G14,L14),2) -> 25.5 | N14: =IF(OR(G14>30,MAX(H14,I14,J14)>100,K14>200),"NAO","SIM") -> SIM | O14: Transportadora | P14: Cabe no limite, mas o frete pelos Correios inviabiliza o preço.
A15: racao-bezerro-inicial-40kg | B15: Ração Bezerro Inicial 18% — Saco 40 kg | C15: Nutriboi | D15: Suplemento e Ração | E15: saco 40 kg | F15: 132 | G15: 40.5 | H15: 70 | I15: 45 | J15: 20 | K15: =H15+I15+J15 -> 135 | L15: =ROUND(H15*I15*J15/6000,2) -> 10.5 | M15: =ROUND(MAX(G15,L15),2) -> 40.5 | N15: =IF(OR(G15>30,MAX(H15,I15,J15)>100,K15>200),"NAO","SIM") -> NAO | O15: Transportadora | P15: 40 kg: acima do limite de 30 kg.
A16: sal-branco-25kg | B16: Sal Branco Grosso Pecuário — Saco 25 kg | C16: Cimsal | D16: Suplemento e Ração | E16: saco 25 kg | F16: 42.9 | G16: 25.5 | H16: 55 | I16: 38 | J16: 15 | K16: =H16+I16+J16 -> 108 | L16: =ROUND(H16*I16*J16/6000,2) -> 5.23 | M16: =ROUND(MAX(G16,L16),2) -> 25.5 | N16: =IF(OR(G16>30,MAX(H16,I16,J16)>100,K16>200),"NAO","SIM") -> SIM | O16: Transportadora | P16: Cabe no limite, mas o frete pelos Correios inviabiliza o preço.
A17: sal-mineral-boi-fos-70-30kg | B17: Sal Mineral Boi FOS 70 — Saco 30 kg | C17: Boi FOS | D17: Suplemento e Ração | E17: saco 30 kg | F17: 149.9 | G17: 30.5 | H17: 60 | I17: 40 | J17: 18 | K17: =H17+I17+J17 -> 118 | L17: =ROUND(H17*I17*J17/6000,2) -> 7.2 | M17: =ROUND(MAX(G17,L17),2) -> 30.5 | N17: =IF(OR(G17>30,MAX(H17,I17,J17)>100,K17>200),"NAO","SIM") -> NAO | O17: Transportadora | P17: Saco de 30 kg estoura o limite de peso dos Correios.
A18: sal-mineral-boi-fos-90-30kg | B18: Sal Mineral Boi FOS 90 Reprodução — Saco 30 kg | C18: Boi FOS | D18: Suplemento e Ração | E18: saco 30 kg | F18: 189.9 | G18: 30.5 | H18: 60 | I18: 40 | J18: 18 | K18: =H18+I18+J18 -> 118 | L18: =ROUND(H18*I18*J18/6000,2) -> 7.2 | M18: =ROUND(MAX(G18,L18),2) -> 30.5 | N18: =IF(OR(G18>30,MAX(H18,I18,J18)>100,K18>200),"NAO","SIM") -> NAO | O18: Transportadora | P18: Saco de 30 kg estoura o limite de peso dos Correios.
A19: carrapaticida-pour-on-1l | B19: Carrapaticida Pour-On — 1 Litro | C19: MSD | D19: Veterinário | E19: frasco | F19: 289.9 | G19: 1.25 | H19: 26 | I19: 12 | J19: 12 | K19: =H19+I19+J19 -> 50 | L19: =ROUND(H19*I19*J19/6000,2) -> 0.62 | M19: =ROUND(MAX(G19,L19),2) -> 1.25 | N19: =IF(OR(G19>30,MAX(H19,I19,J19)>100,K19>200),"NAO","SIM") -> SIM | O19: Correios | P19: Medicamento veterinário: confirmar aceitação e declarar conteúdo.
A20: seringa-veterinaria-50ml | B20: Seringa Veterinária Automática 50 ml | C20: Ideal | D20: Veterinário | E20: unidade | F20: 289 | G20: 0.55 | H20: 32 | I20: 12 | J20: 8 | K20: =H20+I20+J20 -> 52 | L20: =ROUND(H20*I20*J20/6000,2) -> 0.51 | M20: =ROUND(MAX(G20,L20),2) -> 0.55 | N20: =IF(OR(G20>30,MAX(H20,I20,J20)>100,K20>200),"NAO","SIM") -> SIM | O20: Correios
A21: vacina-aftosa-50-doses | B21: Vacina Contra Febre Aftosa — 50 doses | C21: Biogénesis | D21: Veterinário | E21: frasco | F21: 279.9 | G21: 1.5 | H21: 25 | I21: 20 | J21: 20 | K21: =H21+I21+J21 -> 65 | L21: =ROUND(H21*I21*J21/6000,2) -> 1.67 | M21: =ROUND(MAX(G21,L21),2) -> 1.67 | N21: =IF(OR(G21>30,MAX(H21,I21,J21)>100,K21>200),"NAO","SIM") -> SIM | O21: Retirada na loja | P21: Cadeia fria de 2 °C a 8 °C: não pode ser postada.
A22: vermifugo-injetavel-ivermectina-500ml | B22: Vermífugo Injetável Ivermectina 1% — 500 ml | C22: Ourofino | D22: Veterinário | E22: frasco | F22: 219.9 | G22: 0.7 | H22: 22 | I22: 10 | J22: 10 | K22: =H22+I22+J22 -> 42 | L22: =ROUND(H22*I22*J22/6000,2) -> 0.37 | M22: =ROUND(MAX(G22,L22),2) -> 0.7 | N22: =IF(OR(G22>30,MAX(H22,I22,J22)>100,K22>200),"NAO","SIM") -> SIM | O22: Correios | P22: Medicamento veterinário: confirmar aceitação e declarar conteúdo.
A23: vitamina-ade-injetavel-500ml | B23: Vitamina ADE Injetável — 500 ml | C23: Vallée | D23: Veterinário | E23: frasco | F23: 159.9 | G23: 0.7 | H23: 22 | I23: 10 | J23: 10 | K23: =H23+I23+J23 -> 42 | L23: =ROUND(H23*I23*J23/6000,2) -> 0.37 | M23: =ROUND(MAX(G23,L23),2) -> 0.7 | N23: =IF(OR(G23>30,MAX(H23,I23,J23)>100,K23>200),"NAO","SIM") -> SIM | O23: Correios | P23: Medicamento veterinário: confirmar aceitação e declarar conteúdo.
A24: adubo-npk-20-05-20-50kg | B24: Adubo NPK 20-05-20 — Saco 50 kg | C24: Mosaic | D24: Cerca e Insumos | E24: saco 50 kg | F24: 209.9 | G24: 50.5 | H24: 70 | I24: 45 | J24: 22 | K24: =H24+I24+J24 -> 137 | L24: =ROUND(H24*I24*J24/6000,2) -> 11.55 | M24: =ROUND(MAX(G24,L24),2) -> 50.5 | N24: =IF(OR(G24>30,MAX(H24,I24,J24)>100,K24>200),"NAO","SIM") -> NAO | O24: Transportadora | P24: 50 kg: acima do limite de 30 kg.
A25: arame-farpado-500m | B25: Arame Farpado 500 m | C25: Morlan | D25: Cerca e Insumos | E25: rolo | F25: 529.9 | G25: 32 | H25: 40 | I25: 40 | J25: 20 | K25: =H25+I25+J25 -> 100 | L25: =ROUND(H25*I25*J25/6000,2) -> 5.33 | M25: =ROUND(MAX(G25,L25),2) -> 32 | N25: =IF(OR(G25>30,MAX(H25,I25,J25)>100,K25>200),"NAO","SIM") -> NAO | O25: Transportadora | P25: Rolo de 32 kg: acima do limite de 30 kg.
A26: arame-liso-galvanizado-1000m | B26: Arame Liso Galvanizado 2,7 mm — Rolo 1.000 m | C26: Gerdau | D26: Cerca e Insumos | E26: rolo | F26: 649.9 | G26: 45 | H26: 45 | I26: 45 | J26: 20 | K26: =H26+I26+J26 -> 110 | L26: =ROUND(H26*I26*J26/6000,2) -> 6.75 | M26: =ROUND(MAX(G26,L26),2) -> 45 | N26: =IF(OR(G26>30,MAX(H26,I26,J26)>100,K26>200),"NAO","SIM") -> NAO | O26: Transportadora | P26: Rolo de 45 kg: acima do limite de 30 kg.
A27: eletrificador-cerca-100km | B27: Eletrificador de Cerca Rural 100 km | C27: Zebu | D27: Cerca e Insumos | E27: unidade | F27: 1149 | G27: 2.6 | H27: 30 | I27: 25 | J27: 15 | K27: =H27+I27+J27 -> 70 | L27: =ROUND(H27*I27*J27/6000,2) -> 1.88 | M27: =ROUND(MAX(G27,L27),2) -> 2.6 | N27: =IF(OR(G27>30,MAX(H27,I27,J27)>100,K27>200),"NAO","SIM") -> SIM | O27: Correios
A28: semente-brachiaria-brizantha-10kg | B28: Semente Brachiaria Brizantha Marandu — 10 kg | C28: Wolf Seeds | D28: Cerca e Insumos | E28: saco 10 kg | F28: 389.9 | G28: 10.3 | H28: 45 | I28: 30 | J28: 12 | K28: =H28+I28+J28 -> 87 | L28: =ROUND(H28*I28*J28/6000,2) -> 2.7 | M28: =ROUND(MAX(G28,L28),2) -> 10.3 | N28: =IF(OR(G28>30,MAX(H28,I28,J28)>100,K28>200),"NAO","SIM") -> SIM | O28: Correios
A29: bota-couro-vaqueiro | B29: Bota de Couro Vaqueiro Cano Longo | C29: Vimar | D29: Vestuário e Selaria | E29: par | F29: 419.9 | G29: 1.6 | H29: 35 | I29: 25 | J29: 15 | K29: =H29+I29+J29 -> 75 | L29: =ROUND(H29*I29*J29/6000,2) -> 2.19 | M29: =ROUND(MAX(G29,L29),2) -> 2.19 | N29: =IF(OR(G29>30,MAX(H29,I29,J29)>100,K29>200),"NAO","SIM") -> SIM | O29: Correios
A30: cabresto-nylon-com-cabo | B30: Cabresto de Nylon com Cabo 3 m | C30: Boots Horse | D30: Vestuário e Selaria | E30: unidade | F30: 89.9 | G30: 0.4 | H30: 25 | I30: 20 | J30: 10 | K30: =H30+I30+J30 -> 55 | L30: =ROUND(H30*I30*J30/6000,2) -> 0.83 | M30: =ROUND(MAX(G30,L30),2) -> 0.83 | N30: =IF(OR(G30>30,MAX(H30,I30,J30)>100,K30>200),"NAO","SIM") -> SIM | O30: Correios
A31: camisa-uv-campo-manga-longa | B31: Camisa de Campo Manga Longa UV 50+ | C31: Country Work | D31: Vestuário e Selaria | E31: unidade | F31: 129.9 | G31: 0.35 | H31: 30 | I31: 25 | J31: 5 | K31: =H31+I31+J31 -> 60 | L31: =ROUND(H31*I31*J31/6000,2) -> 0.63 | M31: =ROUND(MAX(G31,L31),2) -> 0.63 | N31: =IF(OR(G31>30,MAX(H31,I31,J31)>100,K31>200),"NAO","SIM") -> SIM | O31: Correios
A32: chapeu-palha-country | B32: Chapéu de Palha Country Aba 10 cm | C32: Pralana | D32: Vestuário e Selaria | E32: unidade | F32: 189.9 | G32: 0.45 | H32: 40 | I32: 40 | J32: 20 | K32: =H32+I32+J32 -> 100 | L32: =ROUND(H32*I32*J32/6000,2) -> 5.33 | M32: =ROUND(MAX(G32,L32),2) -> 5.33 | N32: =IF(OR(G32>30,MAX(H32,I32,J32)>100,K32>200),"NAO","SIM") -> SIM | O32: Correios | P32: Leve e volumoso: o frete sai pelo peso cubado (5,3 kg).
A33: sela-australiana-couro | B33: Sela Australiana em Couro | C33: Selaria Campeira | D33: Vestuário e Selaria | E33: unidade | F33: 2890 | G33: 12 | H33: 65 | I33: 50 | J33: 40 | K33: =H33+I33+J33 -> 155 | L33: =ROUND(H33*I33*J33/6000,2) -> 21.67 | M33: =ROUND(MAX(G33,L33),2) -> 21.67 | N33: =IF(OR(G33>30,MAX(H33,I33,J33)>100,K33>200),"NAO","SIM") -> SIM | O33: Transportadora | P33: Cabe no limite, mas a cubagem de 21,7 kg torna o Correios caro demais.
A35: Como as colunas cinzas são calculadas:
A36: - Soma C+L+A = comprimento + largura + altura. Limite dos Correios: 200 cm.
A37: - Peso cubado = C x L x A / 6000 (medidas em cm). É o peso que o volume ocupa.
A38: - Peso taxável = o MAIOR entre o peso real e o cubado. É sobre ele que o frete é cobrado.
A39: - Cabe nos Correios? = NAO quando o peso passa de 30 kg, algum lado passa de 100 cm ou a soma passa de 200 cm.
A40: - Modalidade é decisão comercial: alguns itens cabem nos Correios, mas o frete inviabiliza a venda — esses vão como Transportadora.

Sheet Perfil de postagem
A1: Perfil de postagem — resumo para negociar contrato com os Correios
A2: Tudo abaixo vem da aba Produtos e se atualiza quando você corrigir os pesos.
A4: Divisão do catálogo
A5: Modalidade | B5: Itens | C5: % do catálogo
A6: Correios | B6: =COUNTIF(Produtos!$O$5:$O$33,A6) -> 17 | C6: =IFERROR(B6/$B$9,0) -> 0.5862069
A7: Transportadora | B7: =COUNTIF(Produtos!$O$5:$O$33,A7) -> 11 | C7: =IFERROR(B7/$B$9,0) -> 0.37931034
A8: Retirada na loja | B8: =COUNTIF(Produtos!$O$5:$O$33,A8) -> 1 | C8: =IFERROR(B8/$B$9,0) -> 0.034482759
A9: Total | B9: =SUM(B6:B8) -> 29 | C9: =IFERROR(SUM(C6:C8),0) -> 1
A11: Faixas de peso taxável — só o que vai pelos Correios
A12: Faixa | B12: Itens | C12: % dos itens Correios
A13: Até 1 kg | B13: =COUNTIFS(Produtos!$O$5:$O$33,"Correios",Produtos!$M$5:$M$33,">0",Produtos!$M$5:$M$33,"<=1") -> 8 | C13: =IFERROR(B13/$B$6,0) -> 0.47058824
A14: Acima de 1 até 3 kg | B14: =COUNTIFS(Produtos!$O$5:$O$33,"Correios",Produtos!$M$5:$M$33,">1",Produtos!$M$5:$M$33,"<=3") -> 3 | C14: =IFERROR(B14/$B$6,0) -> 0.17647059
A15: Acima de 3 até 5 kg | B15: =COUNTIFS(Produtos!$O$5:$O$33,"Correios",Produtos!$M$5:$M$33,">3",Produtos!$M$5:$M$33,"<=5") -> 0 | C15: =IFERROR(B15/$B$6,0) -> 0
A16: Acima de 5 até 10 kg | B16: =COUNTIFS(Produtos!$O$5:$O$33,"Correios",Produtos!$M$5:$M$33,">5",Produtos!$M$5:$M$33,"<=10") -> 3 | C16: =IFERROR(B16/$B$6,0) -> 0.17647059
A17: Acima de 10 até 20 kg | B17: =COUNTIFS(Produtos!$O$5:$O$33,"Correios",Produtos!$M$5:$M$33,">10",Produtos!$M$5:$M$33,"<=20") -> 3 | C17: =IFERROR(B17/$B$6,0) -> 0.17647059
A18: Acima de 20 até 30 kg | B18: =COUNTIFS(Produtos!$O$5:$O$33,"Correios",Produtos!$M$5:$M$33,">20",Produtos!$M$5:$M$33,"<=30") -> 0 | C18: =IFERROR(B18/$B$6,0) -> 0
A20: Números para a negociação
A21: Peso taxável médio dos itens Correios (kg) | B21: =IFERROR(ROUND(SUMIF(Produtos!$O$5:$O$33,"Correios",Produtos!$M$5:$M$33)/$B$6,2),0) -> 4.25
A22: Itens em que a cubagem manda no frete | B22: =SUMPRODUCT((Produtos!$O$5:$O$33="Correios")*(Produtos!$L$5:$L$33>Produtos!$G$5:$G$33)) -> 8
A23: Itens que pagam taxa de grande formato (algum lado acima de 70 cm) | B23: =SUMPRODUCT((Produtos!$O$5:$O$33="Correios")*((Produtos!$H$5:$H$33>70)+(Produtos!$I$5:$I$33>70)+(Produtos!$J$5:$J$33>70)>0)) -> 1
A24: Peso total do catálogo Correios, se enviado tudo junto (kg) | B24: =ROUND(SUMIF(Produtos!$O$5:$O$33,"Correios",Produtos!$M$5:$M$33),2) -> 72.27

Sheet Regras Correios
A1: Limites de encomenda dos Correios (PAC / SEDEX)
A2: Verificado em 04/09/2026 nas fontes listadas no fim desta aba. Reconfirmar na agência antes de assinar contrato — os Correios revisam esses limites.
A4: Regra | B4: Valor | C4: O que significa na prática
A5: Peso máximo | B5: 30 kg | C5: Acima disso os Correios não aceitam. Ração de 40 kg e adubo de 50 kg ficam de fora.
A6: Lado máximo | B6: 100 cm | C6: Nenhuma das três medidas pode passar de 100 cm. É o que barra a roçadeira (caixa de 180 cm).
A7: Soma C+L+A máxima | B7: 200 cm | C7: A soma das três medidas juntas.
A8: Caixa mínima | B8: 15 x 10 x 1 cm | C8: Item pequeno precisa ir em caixa maior que o mínimo.
A9: Taxa de grande formato | B9: lado acima de 70 cm | C9: Ainda é aceito, mas encarece. Afeta a lavadora de alta pressão.
A10: Peso cubado | B10: C x L x A / 6000 | C10: Volume convertido em peso. Item leve e grande paga pelo volume, não pelo peso.
A11: Peso taxável | B11: o maior entre real e cubado | C11: É a base do frete. O chapéu de palha pesa 0,45 kg e é cobrado como 5,3 kg.
A14: Fontes consultadas em 04/09/2026
A15: - Correios — Limites de dimensões de embalagens: https://www2.correios.com.br/sistemas/precosprazos/Formato.cfm
A16: - Correios — Envio de encomendas nacionais: https://www.correios.com.br/enviar/encomendas/nacional
A17: - Melhor Envio — Limite de peso nos Correios: https://melhorenvio.com.br/blog/frete-e-logistica/limite-de-peso-correios/
A18: - Loja Integrada — Dimensões máximas e mínimas dos Correios: https://ajuda.lojaintegrada.com.br/pt-BR/articles/6070497
